bayesloop/__init__.py
bayesloop/core.py
bayesloop/exceptions.py
bayesloop/fileIO.py
bayesloop/helper.py
bayesloop/jeffreys.py
bayesloop/observationModels.py
bayesloop/parser.py
bayesloop/preprocessing.py
bayesloop/transitionModels.py
bayesloop-1.5.4.dist-info/LICENSE
bayesloop-1.5.4.dist-info/METADATA
bayesloop-1.5.4.dist-info/WHEEL
bayesloop-1.5.4.dist-info/top_level.txt
bayesloop-1.5.4.dist-info/RECORD
