Metadata-Version: 2.1
Name: bayesloop
Version: 1.5.4
Summary: Probabilistic programming framework that facilitates objective model selection for time-varying parameter models.
Home-page: http://bayesloop.com
Author: Christoph Mark
Author-email: christoph.mark@fau.de
License: The MIT License (MIT)
Download-URL: https://github.com/christophmark/bayesloop/tarball/1.5.4
Keywords: bayes,inference,fitting,model selection,hypothesis testing,time series,time-varying,marginal likelihood
Platform: UNKNOWN
License-File: LICENSE
Requires-Dist: numpy (>=1.11.0)
Requires-Dist: scipy (>=0.17.1)
Requires-Dist: sympy (>=1.0)
Requires-Dist: matplotlib (>=1.5.1)
Requires-Dist: tqdm (>=4.10.0)
Requires-Dist: dill (>=0.2.5)
